{
  "repo_name": "Thien",
  "repo_author": "roooot",
  "repo_icon": "https://github.com/thien-ac.png",
  "fonts": [
    {
      "name": "pinyin 你好",
      "url": "https://github.com/thien-ac/larafonts/raw/refs/heads/main/fonts/pinyinmdc.ttf",
      "format": "truetype"
    },
    {
      "name": "pinyin regular好",
      "url": "https://github.com/thien-ac/larafonts/raw/refs/heads/main/fonts/pinyin-regular.ttf",
      "format": "truetype"
    },  
    {
      "name": "rix love fool",
      "url": "https://github.com/thien-ac/larafonts/raw/refs/heads/main/fonts/rixlovefool.ttf",
      "format": "truetype"
    }
  ]
}
